populate/__init__.py
populate/apps.py
populate/conf.py
populate/define_signals.py
populate/models.py
populate/management/__init__.py
populate/management/commands/__init__.py
populate/management/commands/populate.py
populate/populator/__init__.py
populate/populator/builder.py
populate/populator/loader.py
populate/populator/manager.py
populate/populator/status.py
populate/populator/common/bulk_operations.py
populate/populator/common/errors.py
populate/populator/common/file_manager.py
populate/populator/common/helpers.py
populate/populator/common/populator_actions.py
tests/__init__.py
tests/settings.py
tests/test_models.py
tests/urls.py
lib_exo_populator-0.3.6.dist-info/AUTHORS.rst
lib_exo_populator-0.3.6.dist-info/LICENSE
lib_exo_populator-0.3.6.dist-info/METADATA
lib_exo_populator-0.3.6.dist-info/WHEEL
lib_exo_populator-0.3.6.dist-info/top_level.txt
lib_exo_populator-0.3.6.dist-info/RECORD
