Metadata-Version: 2.1
Name: lib-exo-populator
Version: 0.3.6
Summary: Generic populate models in django from YAML files
Home-page: https://github.com/exolever/lib-exo-populator
Author: Tomas Garzon
Author-email: tomas@openexo.com
License: BSD
Keywords: lib-exo-populator
Platform: UNKNOWN
Classifier: Development Status :: 3 - Alpha
Classifier: Framework :: Django :: 1.11
Classifier: Framework :: Django :: 2.2
Classifier: Intended Audience :: Developers
Classifier: License :: OSI Approved :: BSD License
Classifier: Natural Language :: English
Classifier: Programming Language :: Python :: 3.6
Requires-Dist: singleton-decorator (>=1.0.0)
Requires-Dist: stringcase (>=1.2.0)
